wazuh_api_client/__init__.py
wazuh_api_client/client.py
wazuh_api_client/constants.py
wazuh_api_client/enums.py
wazuh_api_client/exceptions.py
wazuh_api_client/interfaces.py
wazuh_api_client/query.py
wazuh_api_client/response.py
wazuh_api_client/utils.py
wazuh_api_client/endpoints/__init__.py
wazuh_api_client/endpoints/endpoints_v4.py
wazuh_api_client/managers/__init__.py
wazuh_api_client/managers/agents.py
wazuh_api_client/managers/groups.py
wazuh_api_client/managers/syscheck.py
wazuh_api_client/managers/wazuh.py
wazuh_api_client-0.1.0b0.dist-info/licenses/LICENSE
wazuh_api_client-0.1.0b0.dist-info/METADATA
wazuh_api_client-0.1.0b0.dist-info/WHEEL
wazuh_api_client-0.1.0b0.dist-info/top_level.txt
wazuh_api_client-0.1.0b0.dist-info/RECORD
