Metadata-Version: 2.4
Name: wazuh-api-client
Version: 0.1.0b0
Summary: A flexible Python API client for interacting with the Wazuh API (currently supporting version 4).
Author-email: Moad Ennagi <moad.ennagi@gmail.com>
License: Copyright (c) 2018 The Python Packaging Authority
Project-URL: Homepage, https://github.com/moadennagi/wazuh-api-sdk
Classifier: Programming Language :: Python :: 3
Classifier: Operating System :: OS Independent
Requires-Python: >=3.6
License-File: LICENSE
Requires-Dist: requests>=2.20.0
Requires-Dist: httpx==0.28.1
Dynamic: license-file
